textractcaller/__init__.py
textractcaller/_version.py
textractcaller/t_call.py
amazon_textract_caller-0.2.3.dist-info/LICENSE
amazon_textract_caller-0.2.3.dist-info/METADATA
amazon_textract_caller-0.2.3.dist-info/WHEEL
amazon_textract_caller-0.2.3.dist-info/top_level.txt
amazon_textract_caller-0.2.3.dist-info/RECORD
