Metadata-Version: 2.1
Name: amazon-textract-caller
Version: 0.2.3
Summary: Amazon Textract Caller tools
Home-page: https://github.com/aws-samples/amazon-textract-textractor/tree/master/caller
Author: Amazon Rekognition Textract Demoes
Author-email: rekognition-textract-demos@amazon.com
License: Apache License Version 2.0
Keywords: amazon-textract-textractor amazon textract textractor helper caller
Platform: UNKNOWN
Classifier: Development Status :: 4 - Beta
Classifier: Topic :: Utilities
Classifier: License :: OSI Approved :: Apache Software License
Classifier: Programming Language :: Python :: 3.8
Classifier: Programming Language :: Python :: 3.9
Classifier: Programming Language :: Python :: 3.10
Classifier: Programming Language :: Python :: 3.11
Classifier: Programming Language :: Python :: 3.12
Requires-Python: >=3.6
License-File: LICENSE
Requires-Dist: amazon-textract-response-parser (>=0.1.39)
Requires-Dist: boto3 (>=1.26.35)
Requires-Dist: botocore
Provides-Extra: testing
Requires-Dist: amazon-textract-response-parser ; extra == 'testing'
Requires-Dist: pytest ; extra == 'testing'
